{
    "SYS_read":   0,
    "SYS_write":   1,
    "SYS_open":   2,
    "SYS_close":   3,
    "SYS_stat":   4,
    "SYS_fstat":   5,
    "SYS_lstat":   6,
    "SYS_poll":   7,
    "SYS_lseek":   8,
    "SYS_mmap":   9,
    "SYS_mprotect":  10,
    "SYS_munmap":  11,
    "SYS_brk":  12,
    "SYS_rt_sigaction":  13,
    "SYS_rt_sigprocmask":  14,
    "SYS_rt_sigreturn":  15,
    "SYS_ioctl":  16,
    "SYS_pread64":  17,
    "SYS_pwrite64":  18,
    "SYS_readv":  19,
    "SYS_writev":  20,
    "SYS_access":  21,
    "SYS_pipe":  22,
    "SYS_select":  23,
    "SYS_sched_yield":  24,
    "SYS_mremap":  25,
    "SYS_msync":  26,
    "SYS_mincore":  27,
    "SYS_madvise":  28,
    "SYS_shmget":  29,
    "SYS_shmat":  30,
    "SYS_shmctl":  31,
    "SYS_dup":  32,
    "SYS_dup2":  33,
    "SYS_pause":  34,
    "SYS_nanosleep":  35,
    "SYS_getitimer":  36,
    "SYS_alarm":  37,
    "SYS_setitimer":  38,
    "SYS_getpid":  39,
    "SYS_sendfile":  40,
    "SYS_socket":  41,
    "SYS_connect":  42,
    "SYS_accept":  43,
    "SYS_sendto":  44,
    "SYS_recvfrom":  45,
    "SYS_sendmsg":  46,
    "SYS_recvmsg":  47,
    "SYS_shutdown":  48,
    "SYS_bind":  49,
    "SYS_listen":  50,
    "SYS_getsockname":  51,
    "SYS_getpeername":  52,
    "SYS_socketpair":  53,
    "SYS_setsockopt":  54,
    "SYS_getsockopt":  55,
    "SYS_clone":  56,
    "SYS_fork":  57,
    "SYS_vfork":  58,
    "SYS_execve":  59,
    "SYS_exit":  60,
    "SYS_wait4":  61,
    "SYS_kill":  62,
    "SYS_uname":  63,
    "SYS_semget":  64,
    "SYS_semop":  65,
    "SYS_semctl":  66,
    "SYS_shmdt":  67,
    "SYS_msgget":  68,
    "SYS_msgsnd":  69,
    "SYS_msgrcv":  70,
    "SYS_msgctl":  71,
    "SYS_fcntl":  72,
    "SYS_flock":  73,
    "SYS_fsync":  74,
    "SYS_fdatasync":  75,
    "SYS_truncate":  76,
    "SYS_ftruncate":  77,
    "SYS_getdents":  78,
    "SYS_getcwd":  79,
    "SYS_chdir":  80,
    "SYS_fchdir":  81,
    "SYS_rename":  82,
    "SYS_mkdir":  83,
    "SYS_rmdir":  84,
    "SYS_creat":  85,
    "SYS_link":  86,
    "SYS_unlink":  87,
    "SYS_symlink":  88,
    "SYS_readlink":  89,
    "SYS_chmod":  90,
    "SYS_fchmod":  91,
    "SYS_chown":  92,
    "SYS_fchown":  93,
    "SYS_lchown":  94,
    "SYS_umask":  95,
    "SYS_gettimeofday":  96,
    "SYS_getrlimit":  97,
    "SYS_getrusage":  98,
    "SYS_sysinfo":  99,
    "SYS_times": 100,
    "SYS_ptrace": 101,
    "SYS_getuid": 102,
    "SYS_syslog": 103,
    "SYS_getgid": 104,
    "SYS_setuid": 105,
    "SYS_setgid": 106,
    "SYS_geteuid": 107,
    "SYS_getegid": 108,
    "SYS_setpgid": 109,
    "SYS_getppid": 110,
    "SYS_getpgrp": 111,
    "SYS_setsid": 112,
    "SYS_setreuid": 113,
    "SYS_setregid": 114,
    "SYS_getgroups": 115,
    "SYS_setgroups": 116,
    "SYS_setresuid": 117,
    "SYS_getresuid": 118,
    "SYS_setresgid": 119,
    "SYS_getresgid": 120,
    "SYS_getpgid": 121,
    "SYS_setfsuid": 122,
    "SYS_setfsgid": 123,
    "SYS_getsid": 124,
    "SYS_capget": 125,
    "SYS_capset": 126,
    "SYS_rt_sigpending": 127,
    "SYS_rt_sigtimedwait": 128,
    "SYS_rt_sigqueueinfo": 129,
    "SYS_rt_sigsuspend": 130,
    "SYS_sigaltstack": 131,
    "SYS_utime": 132,
    "SYS_mknod": 133,
    "SYS_uselib": 134,
    "SYS_personality": 135,
    "SYS_ustat": 136,
    "SYS_statfs": 137,
    "SYS_fstatfs": 138,
    "SYS_sysfs": 139,
    "SYS_getpriority": 140,
    "SYS_setpriority": 141,
    "SYS_sched_setparam": 142,
    "SYS_sched_getparam": 143,
    "SYS_sched_setscheduler": 144,
    "SYS_sched_getscheduler": 145,
    "SYS_sched_get_priority_max": 146,
    "SYS_sched_get_priority_min": 147,
    "SYS_sched_rr_get_interval": 148,
    "SYS_mlock": 149,
    "SYS_munlock": 150,
    "SYS_mlockall": 151,
    "SYS_munlockall": 152,
    "SYS_vhangup": 153,
    "SYS_modify_ldt": 154,
    "SYS_pivot_root": 155,
    "SYS__sysctl": 156,
    "SYS_prctl": 157,
    "SYS_arch_prctl": 158,
    "SYS_adjtimex": 159,
    "SYS_setrlimit": 160,
    "SYS_chroot": 161,
    "SYS_sync": 162,
    "SYS_acct": 163,
    "SYS_settimeofday": 164,
    "SYS_mount": 165,
    "SYS_umount2": 166,
    "SYS_swapon": 167,
    "SYS_swapoff": 168,
    "SYS_reboot": 169,
    "SYS_sethostname": 170,
    "SYS_setdomainname": 171,
    "SYS_iopl": 172,
    "SYS_ioperm": 173,
    "SYS_create_module": 174,
    "SYS_init_module": 175,
    "SYS_delete_module": 176,
    "SYS_get_kernel_syms": 177,
    "SYS_query_module": 178,
    "SYS_quotactl": 179,
    "SYS_nfsservctl": 180,
    "SYS_getpmsg": 181,
    "SYS_putpmsg": 182,
    "SYS_afs_syscall": 183,
    "SYS_tuxcall": 184,
    "SYS_security": 185,
    "SYS_gettid": 186,
    "SYS_readahead": 187,
    "SYS_setxattr": 188,
    "SYS_lsetxattr": 189,
    "SYS_fsetxattr": 190,
    "SYS_getxattr": 191,
    "SYS_lgetxattr": 192,
    "SYS_fgetxattr": 193,
    "SYS_listxattr": 194,
    "SYS_llistxattr": 195,
    "SYS_flistxattr": 196,
    "SYS_removexattr": 197,
    "SYS_lremovexattr": 198,
    "SYS_fremovexattr": 199,
    "SYS_tkill": 200,
    "SYS_time": 201,
    "SYS_futex": 202,
    "SYS_sched_setaffinity": 203,
    "SYS_sched_getaffinity": 204,
    "SYS_set_thread_area": 205,
    "SYS_io_setup": 206,
    "SYS_io_destroy": 207,
    "SYS_io_getevents": 208,
    "SYS_io_submit": 209,
    "SYS_io_cancel": 210,
    "SYS_get_thread_area": 211,
    "SYS_lookup_dcookie": 212,
    "SYS_epoll_create": 213,
    "SYS_epoll_ctl_old": 214,
    "SYS_epoll_wait_old": 215,
    "SYS_remap_file_pages": 216,
    "SYS_getdents64": 217,
    "SYS_set_tid_address": 218,
    "SYS_restart_syscall": 219,
    "SYS_semtimedop": 220,
    "SYS_fadvise64": 221,
    "SYS_timer_create": 222,
    "SYS_timer_settime": 223,
    "SYS_timer_gettime": 224,
    "SYS_timer_getoverrun": 225,
    "SYS_timer_delete": 226,
    "SYS_clock_settime": 227,
    "SYS_clock_gettime": 228,
    "SYS_clock_getres": 229,
    "SYS_clock_nanosleep": 230,
    "SYS_exit_group": 231,
    "SYS_epoll_wait": 232,
    "SYS_epoll_ctl": 233,
    "SYS_tgkill": 234,
    "SYS_utimes": 235,
    "SYS_vserver": 236,
    "SYS_mbind": 237,
    "SYS_set_mempolicy": 238,
    "SYS_get_mempolicy": 239,
    "SYS_mq_open": 240,
    "SYS_mq_unlink": 241,
    "SYS_mq_timedsend": 242,
    "SYS_mq_timedreceive": 243,
    "SYS_mq_notify": 244,
    "SYS_mq_getsetattr": 245,
    "SYS_kexec_load": 246,
    "SYS_waitid": 247,
    "SYS_add_key": 248,
    "SYS_request_key": 249,
    "SYS_keyctl": 250,
    "SYS_ioprio_set": 251,
    "SYS_ioprio_get": 252,
    "SYS_inotify_init": 253,
    "SYS_inotify_add_watch": 254,
    "SYS_inotify_rm_watch": 255,
    "SYS_migrate_pages": 256,
    "SYS_openat": 257,
    "SYS_mkdirat": 258,
    "SYS_mknodat": 259,
    "SYS_fchownat": 260,
    "SYS_futimesat": 261,
    "SYS_newfstatat": 262,
    "SYS_unlinkat": 263,
    "SYS_renameat": 264,
    "SYS_linkat": 265,
    "SYS_symlinkat": 266,
    "SYS_readlinkat": 267,
    "SYS_fchmodat": 268,
    "SYS_faccessat": 269,
    "SYS_pselect6": 270,
    "SYS_ppoll": 271,
    "SYS_unshare": 272,
    "SYS_set_robust_list": 273,
    "SYS_get_robust_list": 274,
    "SYS_splice": 275,
    "SYS_tee": 276,
    "SYS_sync_file_range": 277,
    "SYS_vmsplice": 278,
    "SYS_move_pages": 279,
    "SYS_utimensat": 280,
    "SYS_epoll_pwait": 281,
    "SYS_signalfd": 282,
    "SYS_timerfd_create": 283,
    "SYS_eventfd": 284,
    "SYS_fallocate": 285,
    "SYS_timerfd_settime": 286,
    "SYS_timerfd_gettime": 287,
    "SYS_accept4": 288,
    "SYS_signalfd4": 289,
    "SYS_eventfd2": 290,
    "SYS_epoll_create1": 291,
    "SYS_dup3": 292,
    "SYS_pipe2": 293,
    "SYS_inotify_init1": 294,
    "SYS_preadv": 295,
    "SYS_pwritev": 296,
    "SYS_rt_tgsigqueueinfo": 297,
    "SYS_perf_event_open": 298,
    "SYS_recvmmsg": 299,
    "SYS_fanotify_init": 300,
    "SYS_fanotify_mark": 301,
    "SYS_prlimit64": 302,
    "SYS_name_to_handle_at": 303,
    "SYS_open_by_handle_at": 304,
    "SYS_clock_adjtime": 305,
    "SYS_syncfs": 306,
    "SYS_sendmmsg": 307,
    "SYS_setns": 308,
    "SYS_getcpu": 309,
    "SYS_process_vm_readv": 310,
    "SYS_process_vm_writev": 311,
    "SYS_kcmp": 312,
    "SYS_finit_module": 313,
    "SYS_sched_setattr": 314,
    "SYS_sched_getattr": 315,
    "SYS_renameat2": 316,
    "SYS_seccomp": 317,
    "SYS_getrandom": 318,
    "SYS_memfd_create": 319,
    "SYS_kexec_file_load": 320,
    "SYS_bpf": 321,
    "SYS_execveat": 322,
    "SYS_userfaultfd": 323,
    "SYS_membarrier": 324,
    "SYS_mlock2": 325,
    "SYS_copy_file_range": 326,
    "SYS_preadv2": 327,
    "SYS_pwritev2": 328,
    "SYS_pkey_mprotect": 329,
    "SYS_pkey_alloc": 330,
    "SYS_pkey_free": 331,
    "SYS_statx": 332,
    "SYS_io_pgetevents": 333,
    "SYS_rseq": 334,
    "SYS_pidfd_send_signal": 424,
    "SYS_io_uring_setup": 425,
    "SYS_io_uring_enter": 426,
    "SYS_io_uring_register": 427,
    "SYS_open_tree": 428,
    "SYS_move_mount": 429,
    "SYS_fsopen": 430,
    "SYS_fsconfig": 431,
    "SYS_fsmount": 432,
    "SYS_fspick": 433,
    "SYS_pidfd_open": 434,
    "SYS_clone3": 435,

    "SYS32_read": 1073741824,
    "SYS32_write": 1073741825,
    "SYS32_open": 1073741826,
    "SYS32_close": 1073741827,
    "SYS32_stat": 1073741828,
    "SYS32_fstat": 1073741829,
    "SYS32_lstat": 1073741830,
    "SYS32_poll": 1073741831,
    "SYS32_lseek": 1073741832,
    "SYS32_mmap": 1073741833,
    "SYS32_mprotect": 1073741834,
    "SYS32_munmap": 1073741835,
    "SYS32_brk": 1073741836,
    "SYS32_rt_sigaction#64": 1073741837,
    "SYS32_rt_sigprocmask": 1073741838,
    "SYS32_rt_sigreturn#64": 1073741839,
    "SYS32_ioctl#64": 1073741840,
    "SYS32_pread64": 1073741841,
    "SYS32_pwrite64": 1073741842,
    "SYS32_readv#64": 1073741843,
    "SYS32_writev#64": 1073741844,
    "SYS32_access": 1073741845,
    "SYS32_pipe": 1073741846,
    "SYS32_select": 1073741847,
    "SYS32_sched_yield": 1073741848,
    "SYS32_mremap": 1073741849,
    "SYS32_msync": 1073741850,
    "SYS32_mincore": 1073741851,
    "SYS32_madvise": 1073741852,
    "SYS32_shmget": 1073741853,
    "SYS32_shmat": 1073741854,
    "SYS32_shmctl": 1073741855,
    "SYS32_dup": 1073741856,
    "SYS32_dup2": 1073741857,
    "SYS32_pause": 1073741858,
    "SYS32_nanosleep": 1073741859,
    "SYS32_getitimer": 1073741860,
    "SYS32_alarm": 1073741861,
    "SYS32_setitimer": 1073741862,
    "SYS32_getpid": 1073741863,
    "SYS32_sendfile": 1073741864,
    "SYS32_socket": 1073741865,
    "SYS32_connect": 1073741866,
    "SYS32_accept": 1073741867,
    "SYS32_sendto": 1073741868,
    "SYS32_recvfrom#64": 1073741869,
    "SYS32_sendmsg#64": 1073741870,
    "SYS32_recvmsg#64": 1073741871,
    "SYS32_shutdown": 1073741872,
    "SYS32_bind": 1073741873,
    "SYS32_listen": 1073741874,
    "SYS32_getsockname": 1073741875,
    "SYS32_getpeername": 1073741876,
    "SYS32_socketpair": 1073741877,
    "SYS32_setsockopt#64": 1073741878,
    "SYS32_getsockopt#64": 1073741879,
    "SYS32_clone": 1073741880,
    "SYS32_fork": 1073741881,
    "SYS32_vfork": 1073741882,
    "SYS32_execve#64": 1073741883,
    "SYS32_exit": 1073741884,
    "SYS32_wait4": 1073741885,
    "SYS32_kill": 1073741886,
    "SYS32_uname": 1073741887,
    "SYS32_semget": 1073741888,
    "SYS32_semop": 1073741889,
    "SYS32_semctl": 1073741890,
    "SYS32_shmdt": 1073741891,
    "SYS32_msgget": 1073741892,
    "SYS32_msgsnd": 1073741893,
    "SYS32_msgrcv": 1073741894,
    "SYS32_msgctl": 1073741895,
    "SYS32_fcntl": 1073741896,
    "SYS32_flock": 1073741897,
    "SYS32_fsync": 1073741898,
    "SYS32_fdatasync": 1073741899,
    "SYS32_truncate": 1073741900,
    "SYS32_ftruncate": 1073741901,
    "SYS32_getdents": 1073741902,
    "SYS32_getcwd": 1073741903,
    "SYS32_chdir": 1073741904,
    "SYS32_fchdir": 1073741905,
    "SYS32_rename": 1073741906,
    "SYS32_mkdir": 1073741907,
    "SYS32_rmdir": 1073741908,
    "SYS32_creat": 1073741909,
    "SYS32_link": 1073741910,
    "SYS32_unlink": 1073741911,
    "SYS32_symlink": 1073741912,
    "SYS32_readlink": 1073741913,
    "SYS32_chmod": 1073741914,
    "SYS32_fchmod": 1073741915,
    "SYS32_chown": 1073741916,
    "SYS32_fchown": 1073741917,
    "SYS32_lchown": 1073741918,
    "SYS32_umask": 1073741919,
    "SYS32_gettimeofday": 1073741920,
    "SYS32_getrlimit": 1073741921,
    "SYS32_getrusage": 1073741922,
    "SYS32_sysinfo": 1073741923,
    "SYS32_times": 1073741924,
    "SYS32_ptrace#64": 1073741925,
    "SYS32_getuid": 1073741926,
    "SYS32_syslog": 1073741927,
    "SYS32_getgid": 1073741928,
    "SYS32_setuid": 1073741929,
    "SYS32_setgid": 1073741930,
    "SYS32_geteuid": 1073741931,
    "SYS32_getegid": 1073741932,
    "SYS32_setpgid": 1073741933,
    "SYS32_getppid": 1073741934,
    "SYS32_getpgrp": 1073741935,
    "SYS32_setsid": 1073741936,
    "SYS32_setreuid": 1073741937,
    "SYS32_setregid": 1073741938,
    "SYS32_getgroups": 1073741939,
    "SYS32_setgroups": 1073741940,
    "SYS32_setresuid": 1073741941,
    "SYS32_getresuid": 1073741942,
    "SYS32_setresgid": 1073741943,
    "SYS32_getresgid": 1073741944,
    "SYS32_getpgid": 1073741945,
    "SYS32_setfsuid": 1073741946,
    "SYS32_setfsgid": 1073741947,
    "SYS32_getsid": 1073741948,
    "SYS32_capget": 1073741949,
    "SYS32_capset": 1073741950,
    "SYS32_rt_sigpending#64": 1073741951,
    "SYS32_rt_sigtimedwait#64": 1073741952,
    "SYS32_rt_sigqueueinfo#64": 1073741953,
    "SYS32_rt_sigsuspend": 1073741954,
    "SYS32_sigaltstack#64": 1073741955,
    "SYS32_utime": 1073741956,
    "SYS32_mknod": 1073741957,
    "SYS32_uselib#64": 1073741958,
    "SYS32_personality": 1073741959,
    "SYS32_ustat": 1073741960,
    "SYS32_statfs": 1073741961,
    "SYS32_fstatfs": 1073741962,
    "SYS32_sysfs": 1073741963,
    "SYS32_getpriority": 1073741964,
    "SYS32_setpriority": 1073741965,
    "SYS32_sched_setparam": 1073741966,
    "SYS32_sched_getparam": 1073741967,
    "SYS32_sched_setscheduler": 1073741968,
    "SYS32_sched_getscheduler": 1073741969,
    "SYS32_sched_get_priority_max": 1073741970,
    "SYS32_sched_get_priority_min": 1073741971,
    "SYS32_sched_rr_get_interval": 1073741972,
    "SYS32_mlock": 1073741973,
    "SYS32_munlock": 1073741974,
    "SYS32_mlockall": 1073741975,
    "SYS32_munlockall": 1073741976,
    "SYS32_vhangup": 1073741977,
    "SYS32_modify_ldt": 1073741978,
    "SYS32_pivot_root": 1073741979,
    "SYS32__sysctl#64": 1073741980,
    "SYS32_prctl": 1073741981,
    "SYS32_arch_prctl": 1073741982,
    "SYS32_adjtimex": 1073741983,
    "SYS32_setrlimit": 1073741984,
    "SYS32_chroot": 1073741985,
    "SYS32_sync": 1073741986,
    "SYS32_acct": 1073741987,
    "SYS32_settimeofday": 1073741988,
    "SYS32_mount": 1073741989,
    "SYS32_umount2": 1073741990,
    "SYS32_swapon": 1073741991,
    "SYS32_swapoff": 1073741992,
    "SYS32_reboot": 1073741993,
    "SYS32_sethostname": 1073741994,
    "SYS32_setdomainname": 1073741995,
    "SYS32_iopl": 1073741996,
    "SYS32_ioperm": 1073741997,
    "SYS32_create_module#64": 1073741998,
    "SYS32_init_module": 1073741999,
    "SYS32_delete_module": 1073742000,
    "SYS32_get_kernel_syms#64": 1073742001,
    "SYS32_query_module#64": 1073742002,
    "SYS32_quotactl": 1073742003,
    "SYS32_nfsservctl#64": 1073742004,
    "SYS32_getpmsg": 1073742005,
    "SYS32_putpmsg": 1073742006,
    "SYS32_afs_syscall": 1073742007,
    "SYS32_tuxcall": 1073742008,
    "SYS32_security": 1073742009,
    "SYS32_gettid": 1073742010,
    "SYS32_readahead": 1073742011,
    "SYS32_setxattr": 1073742012,
    "SYS32_lsetxattr": 1073742013,
    "SYS32_fsetxattr": 1073742014,
    "SYS32_getxattr": 1073742015,
    "SYS32_lgetxattr": 1073742016,
    "SYS32_fgetxattr": 1073742017,
    "SYS32_listxattr": 1073742018,
    "SYS32_llistxattr": 1073742019,
    "SYS32_flistxattr": 1073742020,
    "SYS32_removexattr": 1073742021,
    "SYS32_lremovexattr": 1073742022,
    "SYS32_fremovexattr": 1073742023,
    "SYS32_tkill": 1073742024,
    "SYS32_time": 1073742025,
    "SYS32_futex": 1073742026,
    "SYS32_sched_setaffinity": 1073742027,
    "SYS32_sched_getaffinity": 1073742028,
    "SYS32_set_thread_area#64": 1073742029,
    "SYS32_io_setup#64": 1073742030,
    "SYS32_io_destroy": 1073742031,
    "SYS32_io_getevents": 1073742032,
    "SYS32_io_submit#64": 1073742033,
    "SYS32_io_cancel": 1073742034,
    "SYS32_get_thread_area#64": 1073742035,
    "SYS32_lookup_dcookie": 1073742036,
    "SYS32_epoll_create": 1073742037,
    "SYS32_epoll_ctl_old#64": 1073742038,
    "SYS32_epoll_wait_old#64": 1073742039,
    "SYS32_remap_file_pages": 1073742040,
    "SYS32_getdents64": 1073742041,
    "SYS32_set_tid_address": 1073742042,
    "SYS32_restart_syscall": 1073742043,
    "SYS32_semtimedop": 1073742044,
    "SYS32_fadvise64": 1073742045,
    "SYS32_timer_create#64": 1073742046,
    "SYS32_timer_settime": 1073742047,
    "SYS32_timer_gettime": 1073742048,
    "SYS32_timer_getoverrun": 1073742049,
    "SYS32_timer_delete": 1073742050,
    "SYS32_clock_settime": 1073742051,
    "SYS32_clock_gettime": 1073742052,
    "SYS32_clock_getres": 1073742053,
    "SYS32_clock_nanosleep": 1073742054,
    "SYS32_exit_group": 1073742055,
    "SYS32_epoll_wait": 1073742056,
    "SYS32_epoll_ctl": 1073742057,
    "SYS32_tgkill": 1073742058,
    "SYS32_utimes": 1073742059,
    "SYS32_vserver#64": 1073742060,
    "SYS32_mbind": 1073742061,
    "SYS32_set_mempolicy": 1073742062,
    "SYS32_get_mempolicy": 1073742063,
    "SYS32_mq_open": 1073742064,
    "SYS32_mq_unlink": 1073742065,
    "SYS32_mq_timedsend": 1073742066,
    "SYS32_mq_timedreceive": 1073742067,
    "SYS32_mq_notify#64": 1073742068,
    "SYS32_mq_getsetattr": 1073742069,
    "SYS32_kexec_load#64": 1073742070,
    "SYS32_waitid#64": 1073742071,
    "SYS32_add_key": 1073742072,
    "SYS32_request_key": 1073742073,
    "SYS32_keyctl": 1073742074,
    "SYS32_ioprio_set": 1073742075,
    "SYS32_ioprio_get": 1073742076,
    "SYS32_inotify_init": 1073742078,
    "SYS32_inotify_add_watch": 1073742078,
    "SYS32_inotify_rm_watch": 1073742079,
    "SYS32_migrate_pages": 1073742080,
    "SYS32_openat": 1073742081,
    "SYS32_mkdirat": 1073742082,
    "SYS32_mknodat": 1073742083,
    "SYS32_fchownat": 1073742084,
    "SYS32_futimesat": 1073742085,
    "SYS32_newfstatat": 1073742086,
    "SYS32_unlinkat": 1073742087,
    "SYS32_renameat": 1073742088,
    "SYS32_linkat": 1073742089,
    "SYS32_symlinkat": 1073742090,
    "SYS32_readlinkat": 1073742091,
    "SYS32_fchmodat": 1073742092,
    "SYS32_faccessat": 1073742093,
    "SYS32_pselect6": 1073742094,
    "SYS32_ppoll": 1073742095,
    "SYS32_unshare": 1073742096,
    "SYS32_set_robust_list#64": 1073742097,
    "SYS32_get_robust_list#64": 1073742098,
    "SYS32_splice": 1073742099,
    "SYS32_tee": 1073742100,
    "SYS32_sync_file_range": 1073742101,
    "SYS32_vmsplice#64": 1073742102,
    "SYS32_move_pages#64": 1073742103,
    "SYS32_utimensat": 1073742104,
    "SYS32_epoll_pwait": 1073742105,
    "SYS32_signalfd": 1073742106,
    "SYS32_timerfd_create": 1073742107,
    "SYS32_eventfd": 1073742108,
    "SYS32_fallocate": 1073742109,
    "SYS32_timerfd_settime": 1073742110,
    "SYS32_timerfd_gettime": 1073742111,
    "SYS32_accept4": 1073742112,
    "SYS32_signalfd4": 1073742113,
    "SYS32_eventfd2": 1073742114,
    "SYS32_epoll_create1": 1073742115,
    "SYS32_dup3": 1073742116,
    "SYS32_pipe2": 1073742117,
    "SYS32_inotify_init1": 1073742118,
    "SYS32_preadv#64": 1073742119,
    "SYS32_pwritev#64": 1073742120,
    "SYS32_rt_tgsigqueueinfo#64": 1073742121,
    "SYS32_perf_event_open": 1073742122,
    "SYS32_recvmmsg#64": 1073742123,
    "SYS32_fanotify_init": 1073742124,
    "SYS32_fanotify_mark": 1073742125,
    "SYS32_prlimit64": 1073742126,
    "SYS32_name_to_handle_at": 1073742127,
    "SYS32_open_by_handle_at": 1073742128,
    "SYS32_clock_adjtime": 1073742129,
    "SYS32_syncfs": 1073742130,
    "SYS32_sendmmsg#64": 1073742131,
    "SYS32_setns": 1073742132,
    "SYS32_getcpu": 1073742133,
    "SYS32_process_vm_readv#64": 1073742134,
    "SYS32_process_vm_writev#64": 1073742135,
    "SYS32_kcmp": 1073742136,
    "SYS32_finit_module": 1073742137,
    "SYS32_sched_setattr": 1073742138,
    "SYS32_sched_getattr": 1073742139,
    "SYS32_renameat2": 1073742140,
    "SYS32_seccomp": 1073742141,
    "SYS32_getrandom": 1073742142,
    "SYS32_memfd_create": 1073742143,
    "SYS32_kexec_file_load": 1073742144,
    "SYS32_bpf": 1073742145,
    "SYS32_execveat#64": 1073742146,
    "SYS32_userfaultfd": 1073742147,
    "SYS32_membarrier": 1073742148,
    "SYS32_mlock2": 1073742149,
    "SYS32_copy_file_range": 1073742150,
    "SYS32_preadv2#64": 1073742151,
    "SYS32_pwritev2#64": 1073742152,
    "SYS32_pkey_mprotect": 1073742153,
    "SYS32_pkey_alloc": 1073742154,
    "SYS32_pkey_free": 1073742155,
    "SYS32_statx": 1073742156,
    "SYS32_io_pgetevents": 1073742157,
    "SYS32_rseq": 1073742158,
    "SYS32_pidfd_send_signal": 1073742248,
    "SYS32_io_uring_setup": 1073742249,
    "SYS32_io_uring_enter": 1073742250,
    "SYS32_io_uring_register": 1073742251,
    "SYS32_open_tree": 1073742252,
    "SYS32_move_mount": 1073742253,
    "SYS32_fsopen": 1073742254,
    "SYS32_fsconfig": 1073742255,
    "SYS32_fsmount": 1073742256,
    "SYS32_fspick": 1073742257,
    "SYS32_pidfd_open": 1073742258,
    "SYS32_clone3": 1073742259,
    "SYS32_rt_sigaction": 1073742336,
    "SYS32_rt_sigreturn": 1073742337,
    "SYS32_ioctl": 1073742338,
    "SYS32_readv": 1073742339,
    "SYS32_writev": 1073742340,
    "SYS32_recvfrom": 1073742341,
    "SYS32_sendmsg": 1073742342,
    "SYS32_recvmsg": 1073742343,
    "SYS32_execve": 1073742344,
    "SYS32_ptrace": 1073742345,
    "SYS32_rt_sigpending": 1073742346,
    "SYS32_rt_sigtimedwait": 1073742347,
    "SYS32_rt_sigqueueinfo": 1073742348,
    "SYS32_sigaltstack": 1073742349,
    "SYS32_timer_create": 1073742350,
    "SYS32_mq_notify": 1073742351,
    "SYS32_kexec_load": 1073742352,
    "SYS32_waitid": 1073742353,
    "SYS32_set_robust_list": 1073742354,
    "SYS32_get_robust_list": 1073742355,
    "SYS32_vmsplice": 1073742356,
    "SYS32_move_pages": 1073742357,
    "SYS32_preadv": 1073742358,
    "SYS32_pwritev": 1073742359,
    "SYS32_rt_tgsigqueueinfo": 1073742360,
    "SYS32_recvmmsg": 1073742361,
    "SYS32_sendmmsg": 1073742362,
    "SYS32_process_vm_readv": 1073742363,
    "SYS32_process_vm_writev": 1073742364,
    "SYS32_setsockopt": 1073742365,
    "SYS32_getsockopt": 1073742366,
    "SYS32_io_setup": 1073742367,
    "SYS32_io_submit": 1073742368,
    "SYS32_execveat": 1073742369,
    "SYS32_preadv2": 1073742370,
    "SYS32_pwritev2": 1073742371,

    "SO_TIMESTAMP": 63,
    "SO_TIMESTAMPNS": 64,
    "SO_TIMESTAMPING": 65,
    "SO_RCVTIMEO": 66,
    "SO_SNDTIMEO": 67
}
